LICENSE
README.md
setup.py
Mapviewer_web/MainProcess.py
Mapviewer_web/__init__.py
Mapviewer_web/_version.py
Mapviewer_web/utils/__init__.py
Mapviewer_web/utils/app.py
Mapviewer_web/utils/app_notable.py
Mapviewer_web/utils/helperFunctions.py
Mapviewer_web/utils/loadData.py
Mapviewer_web/utils/plotData.py
mapviewer_web.egg-info/PKG-INFO
mapviewer_web.egg-info/SOURCES.txt
mapviewer_web.egg-info/dependency_links.txt
mapviewer_web.egg-info/entry_points.txt
mapviewer_web.egg-info/not-zip-safe
mapviewer_web.egg-info/requires.txt
mapviewer_web.egg-info/top_level.txt