Metadata-Version: 2.1
Name: mapviewer-web
Version: 1.2.1
Summary: MapViewer-Web: Visualizing galaxy properties from the GIST pipeline products
Home-page: https://github.com/purmortal/mapviewer-web
Author: Zixian Wang (Purmortal)
Author-email: wang.zixian.astro@gmail.com
Classifier: Intended Audience :: Science/Research
Classifier: Topic :: Scientific/Engineering :: Astronomy
Classifier: Programming Language :: Python :: 3
Classifier: License :: OSI Approved :: MIT License
Requires-Python: >=3.6
License-File: LICENSE
Requires-Dist: astropy
Requires-Dist: numpy
Requires-Dist: scipy
Requires-Dist: pandas
Requires-Dist: dash
Requires-Dist: dash_iconify
Requires-Dist: dash-mantine-components==0.12.1
Requires-Dist: dash_ag_grid
Requires-Dist: dash_auth
Requires-Dist: h5py
